py_socialite/__init__.py
py_socialite/exceptions.py
py_socialite/socialite.py
py_socialite-0.0.2.dist-info/METADATA
py_socialite-0.0.2.dist-info/WHEEL
py_socialite-0.0.2.dist-info/top_level.txt
py_socialite-0.0.2.dist-info/RECORD
