Metadata-Version: 2.1
Name: py-socialite
Version: 0.0.2
Summary: A Python package for OAuth authentication with various social providers.
Home-page: https://py-socialite.code4mk.org/
Author: Mostafa Kamal
Author-email: hiremostafa@gmail.com
Project-URL: Source, https://github.com/code4mk/py-socialite
Project-URL: Changelog, https://github.com/code4mk/py-socialite/blob/main/CHANGELOG.md
Keywords: python,oauth,social-auth,authentication,py-socialite,code4mk
Classifier: Development Status :: 3 - Alpha
Classifier: Intended Audience :: Developers
Classifier: License :: OSI Approved :: MIT License
Classifier: Framework :: Django
Classifier: Framework :: Django :: 3.2
Classifier: Programming Language :: Python :: 3
Classifier: Programming Language :: Python :: 3.6
Classifier: Programming Language :: Python :: 3.7
Classifier: Programming Language :: Python :: 3.8
Classifier: Programming Language :: Python :: 3.9
Classifier: Operating System :: OS Independent
Requires-Python: >=3.6
Requires-Dist: requests
Requires-Dist: python-dotenv
